LICENSE
MANIFEST.in
README.md
setup.py
gcimpute/__init__.py
gcimpute/embody.py
gcimpute/func_mean_est.py
gcimpute/gaussian_copula.py
gcimpute/helper_categorical.py
gcimpute/helper_core.py
gcimpute/helper_data.py
gcimpute/helper_evaluation.py
gcimpute/helper_mask.py
gcimpute/low_rank_gaussian_copula.py
gcimpute/marginal_imputation.py
gcimpute/online_transform_function.py
gcimpute/transform_function.py
gcimpute/truncnorm_comp.py
gcimpute.egg-info/PKG-INFO
gcimpute.egg-info/SOURCES.txt
gcimpute.egg-info/dependency_links.txt
gcimpute.egg-info/requires.txt
gcimpute.egg-info/top_level.txt
gcimpute/data/FRED_selected.csv
gcimpute/data/GSS_2014_18var.csv
gcimpute/data/movielens1m_top501.csv
gcimpute/data/winequality-white.csv