Metadata-Version: 2.1
Name: gcimpute
Version: 0.0.4
Summary: A missing value imputation algorithm using the Gaussian copula model
Home-page: https://github.com/udellgroup/gcimpute
Author: Yuxuan Zhao, Eric Landgrebe, Eliot Shekhtman, Madeleiene Udell
Author-email: yz2295@cornell.edu
Maintainer: Yuxuan Zhao
Maintainer-email: yz2295@cornell.edu
License: MIT
Platform: UNKNOWN
Requires-Python: >=3.7
